gofers/__init__.py
gofers/case.py
gofers/fixture.py
gofers/jenkins.py
gofers/loader.py
gofers/main.py
gofers/result.py
gofers/runner.py
gofers/suite.py
gofers/util.py
gofers-0.0.4.dist-info/LICENSE
gofers-0.0.4.dist-info/METADATA
gofers-0.0.4.dist-info/WHEEL
gofers-0.0.4.dist-info/entry_points.txt
gofers-0.0.4.dist-info/top_level.txt
gofers-0.0.4.dist-info/RECORD
