Metadata-Version: 2.1
Name: gofers
Version: 0.0.4
Summary: API test depend Pytest, Yaml, MongoDB, Allure
Home-page: https://github.com/CelebrateMeaningless/Gofers
Author: Wu chao
Author-email: celebratemeaningless@outlook.com
License: MIT
Platform: UNKNOWN
Classifier: License :: OSI Approved :: MIT License
Classifier: Programming Language :: Python
Classifier: Programming Language :: Python :: 3.7
Classifier: Programming Language :: Python :: Implementation :: CPython
Classifier: Programming Language :: Python :: Implementation :: PyPy
Requires-Python: >=3.7.3
Requires-Dist: PyYAML (>=3.13)
